[
  {
    "id": 0,
    "composition": {
      "F": 64,
      "Li": 64
    },
    "lattice_params": {
      "a": 11.463025913947515,
      "b": 11.463025913947515,
      "c": 11.681525898701555,
      "alpha": 90.0,
      "beta": 90.0,
      "gamma": 90.0
    },
    "space_group": 142,
    "properties": {
      "ionic_conductivity": 0.0,
      "bandgap": 0.0,
      "sei_score": 0.7949999999999999,
      "cei_score": 0.7825,
      "bulk_modulus": 0.0
    },
    "objectives": [
      10.0,
      1.0,
      0.1050000000000001,
      0.0675,
      1.0
    ],
    "pareto_rank": 0,
    "crowding_distance": Infinity,
    "generation": 0,
    "parent_ids": [],
    "cif_path": "pareto_electrolyte_ga_results\\cifs\\gen0_F64Li64_3038464872208.cif"
  },
  {
    "id": 1,
    "composition": {
      "Li": 3,
      "F": 3
    },
    "lattice_params": {
      "a": 3.792254775600498,
      "b": 3.7922547756004983,
      "c": 8.71147894717162,
      "alpha": 90.0,
      "beta": 90.0,
      "gamma": 119.99999999999999
    },
    "space_group": 189,
    "properties": {
      "ionic_conductivity": 0.0,
      "bandgap": 0.0,
      "sei_score": 0.7949999999999999,
      "cei_score": 0.7825,
      "bulk_modulus": 0.0
    },
    "objectives": [
      10.0,
      1.0,
      0.1050000000000001,
      0.0675,
      1.0
    ],
    "pareto_rank": 0,
    "crowding_distance": Infinity,
    "generation": 20,
    "parent_ids": [
      3038595022992,
      3038594409552
    ],
    "cif_path": "pareto_electrolyte_ga_results\\cifs\\gen19_F3Li3_3038657683472.cif"
  },
  {
    "id": 2,
    "composition": {
      "Li": 64,
      "F": 64
    },
    "lattice_params": {
      "a": 17.784253949832472,
      "b": 17.784253949832472,
      "c": 7.075155970758282,
      "alpha": 90.0,
      "beta": 90.0,
      "gamma": 90.0
    },
    "space_group": 142,
    "properties": {
      "ionic_conductivity": 0.0,
      "bandgap": 0.0,
      "sei_score": 0.7949999999999999,
      "cei_score": 0.7825,
      "bulk_modulus": 0.0
    },
    "objectives": [
      10.0,
      1.0,
      0.1050000000000001,
      0.0675,
      1.0
    ],
    "pareto_rank": 0,
    "crowding_distance": 0.0,
    "generation": 19,
    "parent_ids": [
      3038464872208,
      3038464872208
    ],
    "cif_path": "pareto_electrolyte_ga_results\\cifs\\gen18_F64Li64_3038615985296.cif"
  },
  {
    "id": 3,
    "composition": {
      "Li": 34,
      "F": 34
    },
    "lattice_params": {
      "a": 9.656015701137715,
      "b": 9.656015701137715,
      "c": 13.985537676550017,
      "alpha": 90.0,
      "beta": 90.0,
      "gamma": 90.0
    },
    "space_group": 123,
    "properties": {
      "ionic_conductivity": 0.0,
      "bandgap": 0.0,
      "sei_score": 0.7949999999999999,
      "cei_score": 0.7825,
      "bulk_modulus": 0.0
    },
    "objectives": [
      10.0,
      1.0,
      0.1050000000000001,
      0.0675,
      1.0
    ],
    "pareto_rank": 0,
    "crowding_distance": 0.0,
    "generation": 18,
    "parent_ids": [
      3038608485072,
      3038608445328
    ],
    "cif_path": "pareto_electrolyte_ga_results\\cifs\\gen17_F34Li34_3038653429840.cif"
  },
  {
    "id": 4,
    "composition": {
      "F": 64,
      "Li": 64
    },
    "lattice_params": {
      "a": 14.10651709178977,
      "b": 14.10651709178977,
      "c": 7.864201499021166,
      "alpha": 90.0,
      "beta": 90.0,
      "gamma": 90.0
    },
    "space_group": 142,
    "properties": {
      "ionic_conductivity": 0.0,
      "bandgap": 0.0,
      "sei_score": 0.7949999999999999,
      "cei_score": 0.7825,
      "bulk_modulus": 0.0
    },
    "objectives": [
      10.0,
      1.0,
      0.1050000000000001,
      0.0675,
      1.0
    ],
    "pareto_rank": 0,
    "crowding_distance": 0.0,
    "generation": 17,
    "parent_ids": [
      3038464693584,
      3038464872208
    ],
    "cif_path": "pareto_electrolyte_ga_results\\cifs\\gen16_F64Li64_3038466144656.cif"
  },
  {
    "id": 5,
    "composition": {
      "Li": 22,
      "F": 22
    },
    "lattice_params": {
      "a": 8.433630019020432,
      "b": 8.433630019020432,
      "c": 6.740899616477719,
      "alpha": 90.0,
      "beta": 90.0,
      "gamma": 119.99999999999999
    },
    "space_group": 149,
    "properties": {
      "ionic_conductivity": 0.0,
      "bandgap": 0.0,
      "sei_score": 0.7949999999999999,
      "cei_score": 0.7825,
      "bulk_modulus": 0.0
    },
    "objectives": [
      10.0,
      1.0,
      0.1050000000000001,
      0.0675,
      1.0
    ],
    "pareto_rank": 0,
    "crowding_distance": 0.0,
    "generation": 16,
    "parent_ids": [
      3038591518864,
      3038564789904
    ],
    "cif_path": "pareto_electrolyte_ga_results\\cifs\\gen15_F22Li22_3038644187600.cif"
  },
  {
    "id": 6,
    "composition": {
      "Li": 44,
      "F": 44
    },
    "lattice_params": {
      "a": 13.749603306746065,
      "b": 13.749603306746065,
      "c": 5.868976329934852,
      "alpha": 90.0,
      "beta": 90.0,
      "gamma": 90.0
    },
    "space_group": 141,
    "properties": {
      "ionic_conductivity": 0.0,
      "bandgap": 0.0,
      "sei_score": 0.7949999999999999,
      "cei_score": 0.7825,
      "bulk_modulus": 0.0
    },
    "objectives": [
      10.0,
      1.0,
      0.1050000000000001,
      0.0675,
      1.0
    ],
    "pareto_rank": 0,
    "crowding_distance": 0.0,
    "generation": 15,
    "parent_ids": [
      3038462690448,
      3038464872208
    ],
    "cif_path": "pareto_electrolyte_ga_results\\cifs\\gen14_F44Li44_3038642281488.cif"
  },
  {
    "id": 7,
    "composition": {
      "Li": 2,
      "F": 2
    },
    "lattice_params": {
      "a": 3.315733471003247,
      "b": 3.315733471003247,
      "c": 6.296571520378416,
      "alpha": 90.0,
      "beta": 90.0,
      "gamma": 119.99999999999999
    },
    "space_group": 149,
    "properties": {
      "ionic_conductivity": 0.0,
      "bandgap": 0.0,
      "sei_score": 0.7949999999999999,
      "cei_score": 0.7825,
      "bulk_modulus": 0.0
    },
    "objectives": [
      10.0,
      1.0,
      0.1050000000000001,
      0.0675,
      1.0
    ],
    "pareto_rank": 0,
    "crowding_distance": 0.0,
    "generation": 14,
    "parent_ids": [
      3038596712784,
      3038591518864
    ],
    "cif_path": "pareto_electrolyte_ga_results\\cifs\\gen13_F2Li2_3038617708944.cif"
  },
  {
    "id": 8,
    "composition": {
      "Li": 64,
      "F": 64
    },
    "lattice_params": {
      "a": 10.230350554073528,
      "b": 10.230350554073528,
      "c": 11.352656634092348,
      "alpha": 90.0,
      "beta": 90.0,
      "gamma": 90.0
    },
    "space_group": 142,
    "properties": {
      "ionic_conductivity": 0.0,
      "bandgap": 0.0,
      "sei_score": 0.7949999999999999,
      "cei_score": 0.7825,
      "bulk_modulus": 0.0
    },
    "objectives": [
      10.0,
      1.0,
      0.1050000000000001,
      0.0675,
      1.0
    ],
    "pareto_rank": 0,
    "crowding_distance": 0.0,
    "generation": 13,
    "parent_ids": [
      3038468821008,
      3038540558480
    ],
    "cif_path": "pareto_electrolyte_ga_results\\cifs\\gen12_F64Li64_3038595093584.cif"
  },
  {
    "id": 9,
    "composition": {
      "Li": 32,
      "F": 32
    },
    "lattice_params": {
      "a": 8.184088616993767,
      "b": 8.184088616993767,
      "c": 9.879800632262441,
      "alpha": 90.0,
      "beta": 90.0,
      "gamma": 90.0
    },
    "space_group": 123,
    "properties": {
      "ionic_conductivity": 0.0,
      "bandgap": 0.0,
      "sei_score": 0.7949999999999999,
      "cei_score": 0.7825,
      "bulk_modulus": 0.0
    },
    "objectives": [
      10.0,
      1.0,
      0.1050000000000001,
      0.0675,
      1.0
    ],
    "pareto_rank": 0,
    "crowding_distance": 0.0,
    "generation": 12,
    "parent_ids": [
      3038464871440,
      3038464506768
    ],
    "cif_path": "pareto_electrolyte_ga_results\\cifs\\gen11_F32Li32_3038613685776.cif"
  },
  {
    "id": 10,
    "composition": {
      "Li": 42,
      "F": 42
    },
    "lattice_params": {
      "a": 8.02427467749614,
      "b": 8.02427467749614,
      "c": 19.881194546881726,
      "alpha": 90.0,
      "beta": 90.0,
      "gamma": 119.99999999999999
    },
    "space_group": 167,
    "properties": {
      "ionic_conductivity": 0.0,
      "bandgap": 0.0,
      "sei_score": 0.7949999999999999,
      "cei_score": 0.7825,
      "bulk_modulus": 0.0
    },
    "objectives": [
      10.0,
      1.0,
      0.1050000000000001,
      0.0675,
      1.0
    ],
    "pareto_rank": 0,
    "crowding_distance": 0.0,
    "generation": 11,
    "parent_ids": [
      3038466855632,
      3038462876368
    ],
    "cif_path": "pareto_electrolyte_ga_results\\cifs\\gen10_F42Li42_3038612600528.cif"
  },
  {
    "id": 11,
    "composition": {
      "F": 64,
      "Li": 16,
      "Ca": 24
    },
    "lattice_params": {
      "a": 12.351517749979493,
      "b": 12.351517749979493,
      "c": 11.771950083140771,
      "alpha": 90.0,
      "beta": 90.0,
      "gamma": 119.99999999999999
    },
    "space_group": 149,
    "properties": {
      "ionic_conductivity": 0.0,
      "bandgap": 0.0,
      "sei_score": 0.7949999999999999,
      "cei_score": 0.7825,
      "bulk_modulus": 0.0
    },
    "objectives": [
      10.0,
      1.0,
      0.1050000000000001,
      0.0675,
      1.0
    ],
    "pareto_rank": 0,
    "crowding_distance": 0.0,
    "generation": 10,
    "parent_ids": [
      3038469948944,
      3038610127824
    ],
    "cif_path": "pareto_electrolyte_ga_results\\cifs\\gen9_Ca24F64Li16_3038581045392.cif"
  },
  {
    "id": 12,
    "composition": {
      "F": 64,
      "Li": 64
    },
    "lattice_params": {
      "a": 12.250206266014827,
      "b": 12.250206266014827,
      "c": 12.250206266014827,
      "alpha": 90.0,
      "beta": 90.0,
      "gamma": 90.0
    },
    "space_group": 216,
    "properties": {
      "ionic_conductivity": 0.0,
      "bandgap": 0.0,
      "sei_score": 0.7949999999999999,
      "cei_score": 0.7825,
      "bulk_modulus": 0.0
    },
    "objectives": [
      10.0,
      1.0,
      0.1050000000000001,
      0.0675,
      1.0
    ],
    "pareto_rank": 0,
    "crowding_distance": 0.0,
    "generation": 9,
    "parent_ids": [
      3038538889744,
      3038541713744
    ],
    "cif_path": "pareto_electrolyte_ga_results\\cifs\\gen8_F64Li64_3038564789904.cif"
  },
  {
    "id": 13,
    "composition": {
      "F": 48,
      "Te": 24,
      "Li": 96
    },
    "lattice_params": {
      "a": 13.712594276949952,
      "b": 13.712594276949952,
      "c": 13.712594276949952,
      "alpha": 90.0,
      "beta": 90.0,
      "gamma": 90.0
    },
    "space_group": 214,
    "properties": {
      "ionic_conductivity": 0.0,
      "bandgap": 0.0,
      "sei_score": 0.7949999999999999,
      "cei_score": 0.7825,
      "bulk_modulus": 0.0
    },
    "objectives": [
      10.0,
      1.0,
      0.1050000000000001,
      0.0675,
      1.0
    ],
    "pareto_rank": 0,
    "crowding_distance": 0.0,
    "generation": 8,
    "parent_ids": [
      3038541713744,
      3038469000976
    ],
    "cif_path": "pareto_electrolyte_ga_results\\cifs\\gen7_F48Li96Te24_3038565430416.cif"
  },
  {
    "id": 14,
    "composition": {
      "Li": 43,
      "F": 43
    },
    "lattice_params": {
      "a": 10.17983649755209,
      "b": 10.17983649755209,
      "c": 12.171713409583989,
      "alpha": 90.0,
      "beta": 90.0,
      "gamma": 90.0
    },
    "space_group": 123,
    "properties": {
      "ionic_conductivity": 0.0,
      "bandgap": 0.0,
      "sei_score": 0.7949999999999999,
      "cei_score": 0.7825,
      "bulk_modulus": 0.0
    },
    "objectives": [
      10.0,
      1.0,
      0.1050000000000001,
      0.0675,
      1.0
    ],
    "pareto_rank": 0,
    "crowding_distance": 0.0,
    "generation": 7,
    "parent_ids": [
      3038407251472,
      3038464872208
    ],
    "cif_path": "pareto_electrolyte_ga_results\\cifs\\gen6_F43Li43_3038464506768.cif"
  },
  {
    "id": 15,
    "composition": {
      "Li": 25,
      "F": 25
    },
    "lattice_params": {
      "a": 7.859963975877,
      "b": 7.859963975877,
      "c": 13.03349780227814,
      "alpha": 90.0,
      "beta": 90.0,
      "gamma": 119.99999999999999
    },
    "space_group": 189,
    "properties": {
      "ionic_conductivity": 0.0,
      "bandgap": 0.0,
      "sei_score": 0.7949999999999999,
      "cei_score": 0.7825,
      "bulk_modulus": 0.0
    },
    "objectives": [
      10.0,
      1.0,
      0.1050000000000001,
      0.0675,
      1.0
    ],
    "pareto_rank": 0,
    "crowding_distance": 0.0,
    "generation": 6,
    "parent_ids": [
      3038608445328,
      3038421017872
    ],
    "cif_path": "pareto_electrolyte_ga_results\\cifs\\gen5_F25Li25_3038591295568.cif"
  },
  {
    "id": 16,
    "composition": {
      "Li": 2,
      "F": 2
    },
    "lattice_params": {
      "a": 5.177849319830554,
      "b": 5.177849319830554,
      "c": 2.0526121173049168,
      "alpha": 90.0,
      "beta": 90.0,
      "gamma": 119.99999999999999
    },
    "space_group": 149,
    "properties": {
      "ionic_conductivity": 0.0,
      "bandgap": 0.0,
      "sei_score": 0.7949999999999999,
      "cei_score": 0.7825,
      "bulk_modulus": 0.0
    },
    "objectives": [
      10.0,
      1.0,
      0.1050000000000001,
      0.0675,
      1.0
    ],
    "pareto_rank": 0,
    "crowding_distance": 0.0,
    "generation": 5,
    "parent_ids": [
      3038408937296,
      3038595022992
    ],
    "cif_path": "pareto_electrolyte_ga_results\\cifs\\gen4_F2Li2_3038591518864.cif"
  },
  {
    "id": 17,
    "composition": {
      "Li": 6,
      "F": 6
    },
    "lattice_params": {
      "a": 6.578180464891623,
      "b": 6.578180464891624,
      "c": 5.09786353085923,
      "alpha": 90.0,
      "beta": 90.0,
      "gamma": 119.99999999999999
    },
    "space_group": 149,
    "properties": {
      "ionic_conductivity": 0.0,
      "bandgap": 0.0,
      "sei_score": 0.7949999999999999,
      "cei_score": 0.7825,
      "bulk_modulus": 0.0
    },
    "objectives": [
      10.0,
      1.0,
      0.1050000000000001,
      0.0675,
      1.0
    ],
    "pareto_rank": 0,
    "crowding_distance": 0.0,
    "generation": 4,
    "parent_ids": [
      3038464871440,
      3038430656592
    ],
    "cif_path": "pareto_electrolyte_ga_results\\cifs\\gen3_F6Li6_3038598067152.cif"
  },
  {
    "id": 18,
    "composition": {
      "F": 8,
      "Li": 8
    },
    "lattice_params": {
      "a": 7.240356541445755,
      "b": 3.8700736997669636,
      "c": 11.02996064279567,
      "alpha": 90.0,
      "beta": 90.0,
      "gamma": 90.0
    },
    "space_group": 55,
    "properties": {
      "ionic_conductivity": 0.0,
      "bandgap": 0.0,
      "sei_score": 0.7949999999999999,
      "cei_score": 0.7825,
      "bulk_modulus": 0.0
    },
    "objectives": [
      10.0,
      1.0,
      0.1050000000000001,
      0.0675,
      1.0
    ],
    "pareto_rank": 0,
    "crowding_distance": 0.0,
    "generation": 3,
    "parent_ids": [
      3038541713744,
      3038464871440
    ],
    "cif_path": "pareto_electrolyte_ga_results\\cifs\\gen2_F8Li8_3038608352848.cif"
  },
  {
    "id": 19,
    "composition": {
      "F": 6,
      "Li": 6
    },
    "lattice_params": {
      "a": 7.91814787021595,
      "b": 7.91814787021595,
      "c": 2.711856200194347,
      "alpha": 90.0,
      "beta": 90.0,
      "gamma": 119.99999999999999
    },
    "space_group": 189,
    "properties": {
      "ionic_conductivity": 0.0,
      "bandgap": 0.0,
      "sei_score": 0.7949999999999999,
      "cei_score": 0.7825,
      "bulk_modulus": 0.0
    },
    "objectives": [
      10.0,
      1.0,
      0.1050000000000001,
      0.0675,
      1.0
    ],
    "pareto_rank": 0,
    "crowding_distance": 0.0,
    "generation": 0,
    "parent_ids": [],
    "cif_path": "pareto_electrolyte_ga_results\\cifs\\gen0_F6Li6_3038463526992.cif"
  },
  {
    "id": 20,
    "composition": {
      "F": 2,
      "Li": 2
    },
    "lattice_params": {
      "a": 3.8953588154961793,
      "b": 3.8953588154961793,
      "c": 4.473984059791512,
      "alpha": 90.0,
      "beta": 90.0,
      "gamma": 119.99999999999999
    },
    "space_group": 149,
    "properties": {
      "ionic_conductivity": 0.0,
      "bandgap": 0.0,
      "sei_score": 0.7949999999999999,
      "cei_score": 0.7825,
      "bulk_modulus": 0.0
    },
    "objectives": [
      10.0,
      1.0,
      0.1050000000000001,
      0.0675,
      1.0
    ],
    "pareto_rank": 0,
    "crowding_distance": 0.0,
    "generation": 0,
    "parent_ids": [],
    "cif_path": "pareto_electrolyte_ga_results\\cifs\\gen0_F2Li2_3038463571600.cif"
  },
  {
    "id": 21,
    "composition": {
      "F": 64,
      "Li": 16,
      "Ca": 24
    },
    "lattice_params": {
      "a": 11.629770088332673,
      "b": 11.629770088332673,
      "c": 10.388922590385253,
      "alpha": 90.0,
      "beta": 90.0,
      "gamma": 90.0
    },
    "space_group": 142,
    "properties": {
      "ionic_conductivity": 0.0,
      "bandgap": 0.0,
      "sei_score": 0.7949999999999999,
      "cei_score": 0.7825,
      "bulk_modulus": 0.0
    },
    "objectives": [
      10.0,
      1.0,
      0.1050000000000001,
      0.0675,
      1.0
    ],
    "pareto_rank": 0,
    "crowding_distance": 0.0,
    "generation": 0,
    "parent_ids": [],
    "cif_path": "pareto_electrolyte_ga_results\\cifs\\gen0_Ca24F64Li16_3038463533072.cif"
  },
  {
    "id": 22,
    "composition": {
      "F": 48,
      "Te": 24,
      "Li": 96
    },
    "lattice_params": {
      "a": 12.528777886713154,
      "b": 12.528777886713154,
      "c": 12.528777886713154,
      "alpha": 90.0,
      "beta": 90.0,
      "gamma": 90.0
    },
    "space_group": 214,
    "properties": {
      "ionic_conductivity": 0.0,
      "bandgap": 0.0,
      "sei_score": 0.7949999999999999,
      "cei_score": 0.7825,
      "bulk_modulus": 0.0
    },
    "objectives": [
      10.0,
      1.0,
      0.1050000000000001,
      0.0675,
      1.0
    ],
    "pareto_rank": 0,
    "crowding_distance": 0.0,
    "generation": 0,
    "parent_ids": [],
    "cif_path": "pareto_electrolyte_ga_results\\cifs\\gen0_F48Li96Te24_3038465566928.cif"
  },
  {
    "id": 23,
    "composition": {
      "F": 8,
      "Li": 8
    },
    "lattice_params": {
      "a": 2.822766215167207,
      "b": 5.308662824119532,
      "c": 8.327259160714448,
      "alpha": 90.0,
      "beta": 90.0,
      "gamma": 90.0
    },
    "space_group": 55,
    "properties": {
      "ionic_conductivity": 0.0,
      "bandgap": 0.0,
      "sei_score": 0.7949999999999999,
      "cei_score": 0.7825,
      "bulk_modulus": 0.0
    },
    "objectives": [
      10.0,
      1.0,
      0.1050000000000001,
      0.0675,
      1.0
    ],
    "pareto_rank": 0,
    "crowding_distance": 0.0,
    "generation": 0,
    "parent_ids": [],
    "cif_path": "pareto_electrolyte_ga_results\\cifs\\gen0_F8Li8_3038464871440.cif"
  },
  {
    "id": 24,
    "composition": {
      "F": 12,
      "Li": 12
    },
    "lattice_params": {
      "a": 7.964452770085531,
      "b": 7.964452770085531,
      "c": 4.94106620311144,
      "alpha": 90.0,
      "beta": 90.0,
      "gamma": 90.0
    },
    "space_group": 123,
    "properties": {
      "ionic_conductivity": 0.0,
      "bandgap": 0.0,
      "sei_score": 0.7949999999999999,
      "cei_score": 0.7825,
      "bulk_modulus": 0.0
    },
    "objectives": [
      10.0,
      1.0,
      0.1050000000000001,
      0.0675,
      1.0
    ],
    "pareto_rank": 0,
    "crowding_distance": 0.0,
    "generation": 0,
    "parent_ids": [],
    "cif_path": "pareto_electrolyte_ga_results\\cifs\\gen0_F12Li12_3038468803664.cif"
  },
  {
    "id": 25,
    "composition": {
      "F": 48,
      "Li": 48
    },
    "lattice_params": {
      "a": 9.923780819467664,
      "b": 9.923780819467664,
      "c": 9.923780819467664,
      "alpha": 90.0,
      "beta": 90.0,
      "gamma": 90.0
    },
    "space_group": 214,
    "properties": {
      "ionic_conductivity": 0.0,
      "bandgap": 0.0,
      "sei_score": 0.7949999999999999,
      "cei_score": 0.7825,
      "bulk_modulus": 0.0
    },
    "objectives": [
      10.0,
      1.0,
      0.1050000000000001,
      0.0675,
      1.0
    ],
    "pareto_rank": 0,
    "crowding_distance": 0.0,
    "generation": 0,
    "parent_ids": [],
    "cif_path": "pareto_electrolyte_ga_results\\cifs\\gen0_F48Li48_3038469000976.cif"
  },
  {
    "id": 26,
    "composition": {
      "F": 12,
      "Li": 12
    },
    "lattice_params": {
      "a": 6.18896567460375,
      "b": 6.18896567460375,
      "c": 5.368637239411285,
      "alpha": 90.0,
      "beta": 90.0,
      "gamma": 90.0
    },
    "space_group": 141,
    "properties": {
      "ionic_conductivity": 0.0,
      "bandgap": 0.0,
      "sei_score": 0.7949999999999999,
      "cei_score": 0.7825,
      "bulk_modulus": 0.0
    },
    "objectives": [
      10.0,
      1.0,
      0.1050000000000001,
      0.0675,
      1.0
    ],
    "pareto_rank": 0,
    "crowding_distance": 0.0,
    "generation": 0,
    "parent_ids": [],
    "cif_path": "pareto_electrolyte_ga_results\\cifs\\gen0_F12Li12_3038469820176.cif"
  },
  {
    "id": 27,
    "composition": {
      "Ca": 18,
      "F": 54,
      "Li": 18
    },
    "lattice_params": {
      "a": 14.062117274095224,
      "b": 14.062117274095224,
      "c": 8.831507106837726,
      "alpha": 90.0,
      "beta": 90.0,
      "gamma": 119.99999999999999
    },
    "space_group": 167,
    "properties": {
      "ionic_conductivity": 0.0,
      "bandgap": 0.0,
      "sei_score": 0.7949999999999999,
      "cei_score": 0.7825,
      "bulk_modulus": 0.0
    },
    "objectives": [
      10.0,
      1.0,
      0.1050000000000001,
      0.0675,
      1.0
    ],
    "pareto_rank": 0,
    "crowding_distance": 0.0,
    "generation": 0,
    "parent_ids": [],
    "cif_path": "pareto_electrolyte_ga_results\\cifs\\gen0_Ca18F54Li18_3038469295888.cif"
  },
  {
    "id": 28,
    "composition": {
      "Li": 12,
      "F": 12
    },
    "lattice_params": {
      "a": 6.523025603830604,
      "b": 6.523025603830604,
      "c": 6.351054069987405,
      "alpha": 90.0,
      "beta": 90.0,
      "gamma": 90.0
    },
    "space_group": 123,
    "properties": {
      "ionic_conductivity": 0.0,
      "bandgap": 0.0,
      "sei_score": 0.7949999999999999,
      "cei_score": 0.7825,
      "bulk_modulus": 0.0
    },
    "objectives": [
      10.0,
      1.0,
      0.1050000000000001,
      0.0675,
      1.0
    ],
    "pareto_rank": 0,
    "crowding_distance": 0.0,
    "generation": 2,
    "parent_ids": [
      3038468803664,
      3038468803664
    ],
    "cif_path": "pareto_electrolyte_ga_results\\cifs\\gen1_F12Li12_3038464338960.cif"
  },
  {
    "id": 29,
    "composition": {
      "F": 12,
      "Li": 12
    },
    "lattice_params": {
      "a": 4.55939516852442,
      "b": 4.55939516852442,
      "c": 13.194460293962866,
      "alpha": 90.0,
      "beta": 90.0,
      "gamma": 90.0
    },
    "space_group": 123,
    "properties": {
      "ionic_conductivity": 0.0,
      "bandgap": 0.0,
      "sei_score": 0.7949999999999999,
      "cei_score": 0.7825,
      "bulk_modulus": 0.0
    },
    "objectives": [
      10.0,
      1.0,
      0.1050000000000001,
      0.0675,
      1.0
    ],
    "pareto_rank": 0,
    "crowding_distance": 0.0,
    "generation": 2,
    "parent_ids": [
      3038468803664,
      3038422303952
    ],
    "cif_path": "pareto_electrolyte_ga_results\\cifs\\gen1_F12Li12_3038430679504.cif"
  },
  {
    "id": 30,
    "composition": {
      "Se": 4,
      "F": 8,
      "Ca": 4,
      "Li": 8
    },
    "lattice_params": {
      "a": 5.101959242672917,
      "b": 9.723127783863495,
      "c": 9.877684471058881,
      "alpha": 90.0,
      "beta": 90.0,
      "gamma": 90.0
    },
    "space_group": 62,
    "properties": {
      "ionic_conductivity": 0.0,
      "bandgap": 0.0,
      "sei_score": 0.7949999999999999,
      "cei_score": 0.7825,
      "bulk_modulus": 0.0
    },
    "objectives": [
      10.0,
      1.0,
      0.1050000000000001,
      0.0675,
      1.0
    ],
    "pareto_rank": 0,
    "crowding_distance": 0.0,
    "generation": 2,
    "parent_ids": [
      3038463430416,
      3038464871440
    ],
    "cif_path": "pareto_electrolyte_ga_results\\cifs\\gen1_Ca4F8Li8Se4_3038422162320.cif"
  },
  {
    "id": 31,
    "composition": {
      "Ca": 18,
      "F": 54,
      "Li": 18
    },
    "lattice_params": {
      "a": 9.392044514373667,
      "b": 9.392044514373667,
      "c": 18.922274049881686,
      "alpha": 90.0,
      "beta": 90.0,
      "gamma": 119.99999999999999
    },
    "space_group": 167,
    "properties": {
      "ionic_conductivity": 0.0,
      "bandgap": 0.0,
      "sei_score": 0.7949999999999999,
      "cei_score": 0.7825,
      "bulk_modulus": 0.0
    },
    "objectives": [
      10.0,
      1.0,
      0.1050000000000001,
      0.0675,
      1.0
    ],
    "pareto_rank": 0,
    "crowding_distance": 0.0,
    "generation": 2,
    "parent_ids": [
      3038469295888,
      3038468083472
    ],
    "cif_path": "pareto_electrolyte_ga_results\\cifs\\gen1_Ca18F54Li18_3038468821008.cif"
  },
  {
    "id": 32,
    "composition": {
      "F": 12,
      "Li": 12
    },
    "lattice_params": {
      "a": 8.804768959571124,
      "b": 8.804768959571124,
      "c": 6.182316804011527,
      "alpha": 90.0,
      "beta": 90.0,
      "gamma": 90.0
    },
    "space_group": 141,
    "properties": {
      "ionic_conductivity": 0.0,
      "bandgap": 0.0,
      "sei_score": 0.7949999999999999,
      "cei_score": 0.7825,
      "bulk_modulus": 0.0
    },
    "objectives": [
      10.0,
      1.0,
      0.1050000000000001,
      0.0675,
      1.0
    ],
    "pareto_rank": 0,
    "crowding_distance": 0.0,
    "generation": 2,
    "parent_ids": [
      3038469820176,
      3038467231504
    ],
    "cif_path": "pareto_electrolyte_ga_results\\cifs\\gen1_F12Li12_3038462690448.cif"
  },
  {
    "id": 33,
    "composition": {
      "Ca": 18,
      "F": 54,
      "Li": 18
    },
    "lattice_params": {
      "a": 10.193905711214782,
      "b": 10.193905711214782,
      "c": 12.107770203838774,
      "alpha": 90.0,
      "beta": 90.0,
      "gamma": 119.99999999999999
    },
    "space_group": 167,
    "properties": {
      "ionic_conductivity": 0.0,
      "bandgap": 0.0,
      "sei_score": 0.7949999999999999,
      "cei_score": 0.7825,
      "bulk_modulus": 0.0
    },
    "objectives": [
      10.0,
      1.0,
      0.1050000000000001,
      0.0675,
      1.0
    ],
    "pareto_rank": 0,
    "crowding_distance": 0.0,
    "generation": 2,
    "parent_ids": [
      3038469295888,
      3038464855504
    ],
    "cif_path": "pareto_electrolyte_ga_results\\cifs\\gen1_Ca18F54Li18_3038462876368.cif"
  },
  {
    "id": 34,
    "composition": {
      "Ca": 18,
      "F": 54,
      "Li": 18
    },
    "lattice_params": {
      "a": 10.583723295386813,
      "b": 10.583723295386813,
      "c": 19.80261862480654,
      "alpha": 90.0,
      "beta": 90.0,
      "gamma": 119.99999999999999
    },
    "space_group": 167,
    "properties": {
      "ionic_conductivity": 0.0,
      "bandgap": 0.0,
      "sei_score": 0.7949999999999999,
      "cei_score": 0.7825,
      "bulk_modulus": 0.0
    },
    "objectives": [
      10.0,
      1.0,
      0.1050000000000001,
      0.0675,
      1.0
    ],
    "pareto_rank": 0,
    "crowding_distance": 0.0,
    "generation": 2,
    "parent_ids": [
      3038469426960,
      3038469295888
    ],
    "cif_path": "pareto_electrolyte_ga_results\\cifs\\gen1_Ca18F54Li18_3038422376912.cif"
  },
  {
    "id": 35,
    "composition": {
      "Li": 12,
      "F": 12
    },
    "lattice_params": {
      "a": 8.143334125107279,
      "b": 8.143334125107279,
      "c": 5.893591723323136,
      "alpha": 90.0,
      "beta": 90.0,
      "gamma": 90.0
    },
    "space_group": 123,
    "properties": {
      "ionic_conductivity": 0.0,
      "bandgap": 0.0,
      "sei_score": 0.7949999999999999,
      "cei_score": 0.7825,
      "bulk_modulus": 0.0
    },
    "objectives": [
      10.0,
      1.0,
      0.1050000000000001,
      0.0675,
      1.0
    ],
    "pareto_rank": 0,
    "crowding_distance": 0.0,
    "generation": 2,
    "parent_ids": [
      3038469820176,
      3038468803664
    ],
    "cif_path": "pareto_electrolyte_ga_results\\cifs\\gen1_F12Li12_3038468312336.cif"
  },
  {
    "id": 36,
    "composition": {
      "F": 2,
      "Li": 2
    },
    "lattice_params": {
      "a": 3.2740897370569417,
      "b": 3.2740897370569417,
      "c": 7.035701382674445,
      "alpha": 90.0,
      "beta": 90.0,
      "gamma": 119.99999999999999
    },
    "space_group": 149,
    "properties": {
      "ionic_conductivity": 0.0,
      "bandgap": 0.0,
      "sei_score": 0.7949999999999999,
      "cei_score": 0.7825,
      "bulk_modulus": 0.0
    },
    "objectives": [
      10.0,
      1.0,
      0.1050000000000001,
      0.0675,
      1.0
    ],
    "pareto_rank": 0,
    "crowding_distance": 0.0,
    "generation": 2,
    "parent_ids": [
      3038468820688,
      3038463571600
    ],
    "cif_path": "pareto_electrolyte_ga_results\\cifs\\gen1_F2Li2_3038408937296.cif"
  },
  {
    "id": 37,
    "composition": {
      "F": 2,
      "Li": 2
    },
    "lattice_params": {
      "a": 2.0965792466970434,
      "b": 2.0965792466970434,
      "c": 7.612827161465594,
      "alpha": 90.0,
      "beta": 90.0,
      "gamma": 119.99999999999999
    },
    "space_group": 149,
    "properties": {
      "ionic_conductivity": 0.0,
      "bandgap": 0.0,
      "sei_score": 0.7949999999999999,
      "cei_score": 0.7825,
      "bulk_modulus": 0.0
    },
    "objectives": [
      10.0,
      1.0,
      0.1050000000000001,
      0.0675,
      1.0
    ],
    "pareto_rank": 0,
    "crowding_distance": 0.0,
    "generation": 2,
    "parent_ids": [
      3038463571600,
      3038465772624
    ],
    "cif_path": "pareto_electrolyte_ga_results\\cifs\\gen1_F2Li2_3038462830800.cif"
  },
  {
    "id": 38,
    "composition": {
      "Li": 5,
      "F": 5
    },
    "lattice_params": {
      "a": 5.5860174249976,
      "b": 5.5860174249976,
      "c": 5.06739118884335,
      "alpha": 90.0,
      "beta": 90.0,
      "gamma": 119.99999999999999
    },
    "space_group": 149,
    "properties": {
      "ionic_conductivity": 0.0,
      "bandgap": 0.0,
      "sei_score": 0.7949999999999999,
      "cei_score": 0.7825,
      "bulk_modulus": 0.0
    },
    "objectives": [
      10.0,
      1.0,
      0.1050000000000001,
      0.0675,
      1.0
    ],
    "pareto_rank": 0,
    "crowding_distance": 0.0,
    "generation": 2,
    "parent_ids": [
      3038468803664,
      3038463571600
    ],
    "cif_path": "pareto_electrolyte_ga_results\\cifs\\gen1_F5Li5_3038463437648.cif"
  },
  {
    "id": 39,
    "composition": {
      "F": 6,
      "Li": 6
    },
    "lattice_params": {
      "a": 2.759040880360073,
      "b": 2.759040880360073,
      "c": 24.473431077359276,
      "alpha": 90.0,
      "beta": 90.0,
      "gamma": 119.99999999999999
    },
    "space_group": 189,
    "properties": {
      "ionic_conductivity": 0.0,
      "bandgap": 0.0,
      "sei_score": 0.7949999999999999,
      "cei_score": 0.7825,
      "bulk_modulus": 0.0
    },
    "objectives": [
      10.0,
      1.0,
      0.1050000000000001,
      0.0675,
      1.0
    ],
    "pareto_rank": 0,
    "crowding_distance": 0.0,
    "generation": 2,
    "parent_ids": [
      3038463526992,
      3038466543376
    ],
    "cif_path": "pareto_electrolyte_ga_results\\cifs\\gen1_F6Li6_3038608310800.cif"
  },
  {
    "id": 40,
    "composition": {
      "F": 48,
      "Te": 24,
      "Li": 96
    },
    "lattice_params": {
      "a": 11.35349657968421,
      "b": 11.35349657968421,
      "c": 21.46977467182906,
      "alpha": 90.0,
      "beta": 90.0,
      "gamma": 119.99999999999999
    },
    "space_group": 167,
    "properties": {
      "ionic_conductivity": 0.0,
      "bandgap": 0.0,
      "sei_score": 0.7949999999999999,
      "cei_score": 0.7825,
      "bulk_modulus": 0.0
    },
    "objectives": [
      10.0,
      1.0,
      0.1050000000000001,
      0.0675,
      1.0
    ],
    "pareto_rank": 0,
    "crowding_distance": 0.0,
    "generation": 2,
    "parent_ids": [
      3038469295888,
      3038465566928
    ],
    "cif_path": "pareto_electrolyte_ga_results\\cifs\\gen1_F48Li96Te24_3038464874896.cif"
  },
  {
    "id": 41,
    "composition": {
      "Ca": 18,
      "F": 54,
      "Li": 18
    },
    "lattice_params": {
      "a": 10.315288526745203,
      "b": 10.315288526745203,
      "c": 21.23066570053805,
      "alpha": 90.0,
      "beta": 90.0,
      "gamma": 119.99999999999999
    },
    "space_group": 167,
    "properties": {
      "ionic_conductivity": 0.0,
      "bandgap": 0.0,
      "sei_score": 0.7949999999999999,
      "cei_score": 0.7825,
      "bulk_modulus": 0.0
    },
    "objectives": [
      10.0,
      1.0,
      0.1050000000000001,
      0.0675,
      1.0
    ],
    "pareto_rank": 0,
    "crowding_distance": 0.0,
    "generation": 2,
    "parent_ids": [
      3038468251344,
      3038469295888
    ],
    "cif_path": "pareto_electrolyte_ga_results\\cifs\\gen1_Ca18F54Li18_3038596009488.cif"
  },
  {
    "id": 42,
    "composition": {
      "F": 12,
      "Li": 12
    },
    "lattice_params": {
      "a": 7.103104724013208,
      "b": 7.103104724013208,
      "c": 5.7695262531599765,
      "alpha": 90.0,
      "beta": 90.0,
      "gamma": 90.0
    },
    "space_group": 123,
    "properties": {
      "ionic_conductivity": 0.0,
      "bandgap": 0.0,
      "sei_score": 0.7949999999999999,
      "cei_score": 0.7825,
      "bulk_modulus": 0.0
    },
    "objectives": [
      10.0,
      1.0,
      0.1050000000000001,
      0.0675,
      1.0
    ],
    "pareto_rank": 0,
    "crowding_distance": 0.0,
    "generation": 2,
    "parent_ids": [
      3038468312848,
      3038468803664
    ],
    "cif_path": "pareto_electrolyte_ga_results\\cifs\\gen1_F12Li12_3038422156304.cif"
  },
  {
    "id": 43,
    "composition": {
      "Li": 9,
      "F": 9
    },
    "lattice_params": {
      "a": 7.051127607647684,
      "b": 7.051127607647684,
      "c": 4.9706941823065875,
      "alpha": 90.0,
      "beta": 90.0,
      "gamma": 90.0
    },
    "space_group": 123,
    "properties": {
      "ionic_conductivity": 0.0,
      "bandgap": 0.0,
      "sei_score": 0.7949999999999999,
      "cei_score": 0.7825,
      "bulk_modulus": 0.0
    },
    "objectives": [
      10.0,
      1.0,
      0.1050000000000001,
      0.0675,
      1.0
    ],
    "pareto_rank": 0,
    "crowding_distance": 0.0,
    "generation": 2,
    "parent_ids": [
      3038463526992,
      3038468803664
    ],
    "cif_path": "pareto_electrolyte_ga_results\\cifs\\gen1_F9Li9_3038595580944.cif"
  },
  {
    "id": 44,
    "composition": {
      "F": 2,
      "Li": 2
    },
    "lattice_params": {
      "a": 2.7861669662818365,
      "b": 2.7861669662818365,
      "c": 3.315814742645588,
      "alpha": 90.0,
      "beta": 90.0,
      "gamma": 119.99999999999999
    },
    "space_group": 149,
    "properties": {
      "ionic_conductivity": 0.0,
      "bandgap": 0.0,
      "sei_score": 0.7949999999999999,
      "cei_score": 0.7825,
      "bulk_modulus": 0.0
    },
    "objectives": [
      10.0,
      1.0,
      0.1050000000000001,
      0.0675,
      1.0
    ],
    "pareto_rank": 0,
    "crowding_distance": 0.0,
    "generation": 2,
    "parent_ids": [
      3038463533072,
      3038463571600
    ],
    "cif_path": "pareto_electrolyte_ga_results\\cifs\\gen1_F2Li2_3038468859600.cif"
  },
  {
    "id": 45,
    "composition": {
      "F": 12,
      "Li": 12
    },
    "lattice_params": {
      "a": 7.253679449723834,
      "b": 7.253679449723834,
      "c": 5.652437530685378,
      "alpha": 90.0,
      "beta": 90.0,
      "gamma": 90.0
    },
    "space_group": 123,
    "properties": {
      "ionic_conductivity": 0.0,
      "bandgap": 0.0,
      "sei_score": 0.7949999999999999,
      "cei_score": 0.7825,
      "bulk_modulus": 0.0
    },
    "objectives": [
      10.0,
      1.0,
      0.1050000000000001,
      0.0675,
      1.0
    ],
    "pareto_rank": 0,
    "crowding_distance": 0.0,
    "generation": 2,
    "parent_ids": [
      3038468803664,
      3038466543376
    ],
    "cif_path": "pareto_electrolyte_ga_results\\cifs\\gen1_F12Li12_3038596767120.cif"
  },
  {
    "id": 46,
    "composition": {
      "F": 64,
      "Li": 16,
      "Ca": 24
    },
    "lattice_params": {
      "a": 12.332531845410692,
      "b": 12.332531845410692,
      "c": 10.9713190126355,
      "alpha": 90.0,
      "beta": 90.0,
      "gamma": 90.0
    },
    "space_group": 142,
    "properties": {
      "ionic_conductivity": 0.0,
      "bandgap": 0.0,
      "sei_score": 0.7949999999999999,
      "cei_score": 0.7825,
      "bulk_modulus": 0.0
    },
    "objectives": [
      10.0,
      1.0,
      0.1050000000000001,
      0.0675,
      1.0
    ],
    "pareto_rank": 0,
    "crowding_distance": 0.0,
    "generation": 2,
    "parent_ids": [
      3038469000976,
      3038463533072
    ],
    "cif_path": "pareto_electrolyte_ga_results\\cifs\\gen1_Ca24F64Li16_3038469948944.cif"
  },
  {
    "id": 47,
    "composition": {
      "Li": 9,
      "F": 9
    },
    "lattice_params": {
      "a": 4.3062764047779165,
      "b": 4.3062764047779165,
      "c": 16.354248913656736,
      "alpha": 90.0,
      "beta": 90.0,
      "gamma": 90.0
    },
    "space_group": 123,
    "properties": {
      "ionic_conductivity": 0.0,
      "bandgap": 0.0,
      "sei_score": 0.7949999999999999,
      "cei_score": 0.7825,
      "bulk_modulus": 0.0
    },
    "objectives": [
      10.0,
      1.0,
      0.1050000000000001,
      0.0675,
      1.0
    ],
    "pareto_rank": 0,
    "crowding_distance": 0.0,
    "generation": 2,
    "parent_ids": [
      3038463526992,
      3038468803664
    ],
    "cif_path": "pareto_electrolyte_ga_results\\cifs\\gen1_F9Li9_3038596772880.cif"
  },
  {
    "id": 48,
    "composition": {
      "Li": 30,
      "F": 30
    },
    "lattice_params": {
      "a": 9.768096911312112,
      "b": 13.904258062912406,
      "c": 8.289020103889552,
      "alpha": 90.0,
      "beta": 90.0,
      "gamma": 90.0
    },
    "space_group": 55,
    "properties": {
      "ionic_conductivity": 0.0,
      "bandgap": 0.0,
      "sei_score": 0.7949999999999999,
      "cei_score": 0.7825,
      "bulk_modulus": 0.0
    },
    "objectives": [
      10.0,
      1.0,
      0.1050000000000001,
      0.0675,
      1.0
    ],
    "pareto_rank": 0,
    "crowding_distance": 0.0,
    "generation": 2,
    "parent_ids": [
      3038469000976,
      3038464871440
    ],
    "cif_path": "pareto_electrolyte_ga_results\\cifs\\gen1_F30Li30_3038607774032.cif"
  },
  {
    "id": 49,
    "composition": {
      "F": 48,
      "Li": 48
    },
    "lattice_params": {
      "a": 13.896094442513032,
      "b": 13.896094442513032,
      "c": 7.849764452782197,
      "alpha": 90.0,
      "beta": 90.0,
      "gamma": 119.99999999999999
    },
    "space_group": 176,
    "properties": {
      "ionic_conductivity": 0.0,
      "bandgap": 0.0,
      "sei_score": 0.7949999999999999,
      "cei_score": 0.7825,
      "bulk_modulus": 0.0
    },
    "objectives": [
      10.0,
      1.0,
      0.1050000000000001,
      0.0675,
      1.0
    ],
    "pareto_rank": 0,
    "crowding_distance": 0.0,
    "generation": 2,
    "parent_ids": [
      3038465775248,
      3038469000976
    ],
    "cif_path": "pareto_electrolyte_ga_results\\cifs\\gen1_F48Li48_3038469538448.cif"
  },
  {
    "id": 50,
    "composition": {
      "F": 8,
      "Li": 8
    },
    "lattice_params": {
      "a": 7.526415475065177,
      "b": 7.526415475065177,
      "c": 4.051885983553442,
      "alpha": 90.0,
      "beta": 90.0,
      "gamma": 90.0
    },
    "space_group": 142,
    "properties": {
      "ionic_conductivity": 0.0,
      "bandgap": 0.0,
      "sei_score": 0.7949999999999999,
      "cei_score": 0.7825,
      "bulk_modulus": 0.0
    },
    "objectives": [
      10.0,
      1.0,
      0.1050000000000001,
      0.0675,
      1.0
    ],
    "pareto_rank": 0,
    "crowding_distance": 0.0,
    "generation": 2,
    "parent_ids": [
      3038464871440,
      3038463533072
    ],
    "cif_path": "pareto_electrolyte_ga_results\\cifs\\gen1_F8Li8_3038466867088.cif"
  },
  {
    "id": 51,
    "composition": {
      "F": 64,
      "Li": 64
    },
    "lattice_params": {
      "a": 10.871339827015001,
      "b": 10.871339827015001,
      "c": 9.26095012053411,
      "alpha": 90.0,
      "beta": 90.0,
      "gamma": 90.0
    },
    "space_group": 142,
    "properties": {
      "ionic_conductivity": 0.0,
      "bandgap": 0.0,
      "sei_score": 0.7949999999999999,
      "cei_score": 0.7825,
      "bulk_modulus": 0.0
    },
    "objectives": [
      10.0,
      1.0,
      0.1050000000000001,
      0.0675,
      1.0
    ],
    "pareto_rank": 0,
    "crowding_distance": 0.0,
    "generation": 2,
    "parent_ids": [
      3038468820112,
      3038464872208
    ],
    "cif_path": "pareto_electrolyte_ga_results\\cifs\\gen1_F64Li64_3038469968528.cif"
  },
  {
    "id": 52,
    "composition": {
      "Li": 3,
      "F": 3
    },
    "lattice_params": {
      "a": 4.173101356181125,
      "b": 4.173101356181125,
      "c": 6.6553859034329195,
      "alpha": 90.0,
      "beta": 90.0,
      "gamma": 119.99999999999999
    },
    "space_group": 149,
    "properties": {
      "ionic_conductivity": 0.0,
      "bandgap": 0.0,
      "sei_score": 0.7949999999999999,
      "cei_score": 0.7825,
      "bulk_modulus": 0.0
    },
    "objectives": [
      10.0,
      1.0,
      0.1050000000000001,
      0.0675,
      1.0
    ],
    "pareto_rank": 0,
    "crowding_distance": 0.0,
    "generation": 2,
    "parent_ids": [
      3038464871440,
      3038463571600
    ],
    "cif_path": "pareto_electrolyte_ga_results\\cifs\\gen1_F3Li3_3038596712784.cif"
  },
  {
    "id": 53,
    "composition": {
      "F": 12,
      "Li": 12
    },
    "lattice_params": {
      "a": 6.607737314583155,
      "b": 6.607737314583155,
      "c": 8.587232030605024,
      "alpha": 90.0,
      "beta": 90.0,
      "gamma": 90.0
    },
    "space_group": 123,
    "properties": {
      "ionic_conductivity": 0.0,
      "bandgap": 0.0,
      "sei_score": 0.7949999999999999,
      "cei_score": 0.7825,
      "bulk_modulus": 0.0
    },
    "objectives": [
      10.0,
      1.0,
      0.1050000000000001,
      0.0675,
      1.0
    ],
    "pareto_rank": 0,
    "crowding_distance": 0.0,
    "generation": 2,
    "parent_ids": [
      3038468803664,
      3038422303952
    ],
    "cif_path": "pareto_electrolyte_ga_results\\cifs\\gen1_F12Li12_3038608485072.cif"
  },
  {
    "id": 54,
    "composition": {
      "Li": 36,
      "F": 36
    },
    "lattice_params": {
      "a": 9.64112533730926,
      "b": 9.64112533730926,
      "c": 9.64112533730926,
      "alpha": 90.0,
      "beta": 90.0,
      "gamma": 90.0
    },
    "space_group": 214,
    "properties": {
      "ionic_conductivity": 0.0,
      "bandgap": 0.0,
      "sei_score": 0.7949999999999999,
      "cei_score": 0.7825,
      "bulk_modulus": 0.0
    },
    "objectives": [
      10.0,
      1.0,
      0.1050000000000001,
      0.0675,
      1.0
    ],
    "pareto_rank": 0,
    "crowding_distance": 0.0,
    "generation": 2,
    "parent_ids": [
      3038469000976,
      3038468803664
    ],
    "cif_path": "pareto_electrolyte_ga_results\\cifs\\gen1_F36Li36_3038589929296.cif"
  },
  {
    "id": 55,
    "composition": {
      "F": 48,
      "Li": 48
    },
    "lattice_params": {
      "a": 10.994747633604833,
      "b": 10.994747633604833,
      "c": 10.994747633604833,
      "alpha": 90.0,
      "beta": 90.0,
      "gamma": 90.0
    },
    "space_group": 214,
    "properties": {
      "ionic_conductivity": 0.0,
      "bandgap": 0.0,
      "sei_score": 0.7949999999999999,
      "cei_score": 0.7825,
      "bulk_modulus": 0.0
    },
    "objectives": [
      10.0,
      1.0,
      0.1050000000000001,
      0.0675,
      1.0
    ],
    "pareto_rank": 0,
    "crowding_distance": 0.0,
    "generation": 2,
    "parent_ids": [
      3038469000976,
      3038422172432
    ],
    "cif_path": "pareto_electrolyte_ga_results\\cifs\\gen1_F48Li48_3038608936144.cif"
  },
  {
    "id": 56,
    "composition": {
      "F": 48,
      "Te": 24,
      "Li": 96
    },
    "lattice_params": {
      "a": 12.93213564568826,
      "b": 12.93213564568826,
      "c": 12.93213564568826,
      "alpha": 90.0,
      "beta": 90.0,
      "gamma": 90.0
    },
    "space_group": 216,
    "properties": {
      "ionic_conductivity": 0.0,
      "bandgap": 0.0,
      "sei_score": 0.7949999999999999,
      "cei_score": 0.7825,
      "bulk_modulus": 0.0
    },
    "objectives": [
      10.0,
      1.0,
      0.1050000000000001,
      0.0675,
      1.0
    ],
    "pareto_rank": 0,
    "crowding_distance": 0.0,
    "generation": 2,
    "parent_ids": [
      3038465566928,
      3038466543376
    ],
    "cif_path": "pareto_electrolyte_ga_results\\cifs\\gen1_F48Li96Te24_3038541713744.cif"
  },
  {
    "id": 57,
    "composition": {
      "F": 2,
      "Li": 2
    },
    "lattice_params": {
      "a": 3.31972691945924,
      "b": 3.31972691945924,
      "c": 4.981247424862304,
      "alpha": 90.0,
      "beta": 90.0,
      "gamma": 119.99999999999999
    },
    "space_group": 194,
    "properties": {
      "ionic_conductivity": 0.0,
      "bandgap": 0.0,
      "sei_score": 0.7949999999999999,
      "cei_score": 0.7825,
      "bulk_modulus": 0.0
    },
    "objectives": [
      10.0,
      1.0,
      0.1050000000000001,
      0.0675,
      1.0
    ],
    "pareto_rank": 0,
    "crowding_distance": 0.0,
    "generation": 2,
    "parent_ids": [
      3038468757712,
      3038463571600
    ],
    "cif_path": "pareto_electrolyte_ga_results\\cifs\\gen1_F2Li2_3038596803216.cif"
  },
  {
    "id": 58,
    "composition": {
      "F": 8,
      "Li": 8
    },
    "lattice_params": {
      "a": 11.201632934083525,
      "b": 3.2724191390627806,
      "c": 6.345044348390431,
      "alpha": 90.0,
      "beta": 90.0,
      "gamma": 90.0
    },
    "space_group": 70,
    "properties": {
      "ionic_conductivity": 0.0,
      "bandgap": 0.0,
      "sei_score": 0.7949999999999999,
      "cei_score": 0.7825,
      "bulk_modulus": 0.0
    },
    "objectives": [
      10.0,
      1.0,
      0.1050000000000001,
      0.0675,
      1.0
    ],
    "pareto_rank": 0,
    "crowding_distance": 0.0,
    "generation": 2,
    "parent_ids": [
      3038464871440,
      3038463201040
    ],
    "cif_path": "pareto_electrolyte_ga_results\\cifs\\gen1_F8Li8_3038541686608.cif"
  },
  {
    "id": 59,
    "composition": {
      "Li": 10,
      "F": 10
    },
    "lattice_params": {
      "a": 4.6848244694347,
      "b": 8.286497812299237,
      "c": 7.618085402744671,
      "alpha": 90.0,
      "beta": 90.0,
      "gamma": 90.0
    },
    "space_group": 55,
    "properties": {
      "ionic_conductivity": 0.0,
      "bandgap": 0.0,
      "sei_score": 0.7949999999999999,
      "cei_score": 0.7825,
      "bulk_modulus": 0.0
    },
    "objectives": [
      10.0,
      1.0,
      0.1050000000000001,
      0.0675,
      1.0
    ],
    "pareto_rank": 0,
    "crowding_distance": 0.0,
    "generation": 2,
    "parent_ids": [
      3038464871440,
      3038469820176
    ],
    "cif_path": "pareto_electrolyte_ga_results\\cifs\\gen1_F10Li10_3038539774928.cif"
  },
  {
    "id": 60,
    "composition": {
      "F": 64,
      "Li": 64
    },
    "lattice_params": {
      "a": 12.299448130546208,
      "b": 12.299448130546208,
      "c": 7.5486668942793695,
      "alpha": 90.0,
      "beta": 90.0,
      "gamma": 90.0
    },
    "space_group": 142,
    "properties": {
      "ionic_conductivity": 0.0,
      "bandgap": 0.0,
      "sei_score": 0.7949999999999999,
      "cei_score": 0.7825,
      "bulk_modulus": 0.0
    },
    "objectives": [
      10.0,
      1.0,
      0.1050000000000001,
      0.0675,
      1.0
    ],
    "pareto_rank": 0,
    "crowding_distance": 0.0,
    "generation": 2,
    "parent_ids": [
      3038463533072,
      3038464872208
    ],
    "cif_path": "pareto_electrolyte_ga_results\\cifs\\gen1_F64Li64_3038608445328.cif"
  },
  {
    "id": 61,
    "composition": {
      "F": 64,
      "Li": 64
    },
    "lattice_params": {
      "a": 11.127447363923448,
      "b": 11.127447363923448,
      "c": 15.09187352902882,
      "alpha": 90.0,
      "beta": 90.0,
      "gamma": 90.0
    },
    "space_group": 142,
    "properties": {
      "ionic_conductivity": 0.0,
      "bandgap": 0.0,
      "sei_score": 0.7949999999999999,
      "cei_score": 0.7825,
      "bulk_modulus": 0.0
    },
    "objectives": [
      10.0,
      1.0,
      0.1050000000000001,
      0.0675,
      1.0
    ],
    "pareto_rank": 0,
    "crowding_distance": 0.0,
    "generation": 2,
    "parent_ids": [
      3038464872208,
      3038466543376
    ],
    "cif_path": "pareto_electrolyte_ga_results\\cifs\\gen1_F64Li64_3038538889744.cif"
  },
  {
    "id": 62,
    "composition": {
      "F": 48,
      "Te": 24,
      "Li": 96
    },
    "lattice_params": {
      "a": 13.792158838644843,
      "b": 13.792158838644843,
      "c": 13.792158838644843,
      "alpha": 90.0,
      "beta": 90.0,
      "gamma": 90.0
    },
    "space_group": 214,
    "properties": {
      "ionic_conductivity": 0.0,
      "bandgap": 0.0,
      "sei_score": 0.7949999999999999,
      "cei_score": 0.7825,
      "bulk_modulus": 0.0
    },
    "objectives": [
      10.0,
      1.0,
      0.1050000000000001,
      0.0675,
      1.0
    ],
    "pareto_rank": 0,
    "crowding_distance": 0.0,
    "generation": 2,
    "parent_ids": [
      3038468803664,
      3038465566928
    ],
    "cif_path": "pareto_electrolyte_ga_results\\cifs\\gen1_F48Li96Te24_3038540845776.cif"
  },
  {
    "id": 63,
    "composition": {
      "Li": 34,
      "F": 34
    },
    "lattice_params": {
      "a": 6.576981280630404,
      "b": 12.069092824151157,
      "c": 8.960490712957014,
      "alpha": 90.0,
      "beta": 90.0,
      "gamma": 90.0
    },
    "space_group": 55,
    "properties": {
      "ionic_conductivity": 0.0,
      "bandgap": 0.0,
      "sei_score": 0.7949999999999999,
      "cei_score": 0.7825,
      "bulk_modulus": 0.0
    },
    "objectives": [
      10.0,
      1.0,
      0.1050000000000001,
      0.0675,
      1.0
    ],
    "pareto_rank": 0,
    "crowding_distance": 0.0,
    "generation": 2,
    "parent_ids": [
      3038464871440,
      3038464872208
    ],
    "cif_path": "pareto_electrolyte_ga_results\\cifs\\gen1_F34Li34_3038594667920.cif"
  },
  {
    "id": 64,
    "composition": {
      "Li": 64,
      "F": 64
    },
    "lattice_params": {
      "a": 20.864421903390205,
      "b": 20.864421903390205,
      "c": 2.336357052550116,
      "alpha": 90.0,
      "beta": 90.0,
      "gamma": 90.0
    },
    "space_group": 142,
    "properties": {
      "ionic_conductivity": 0.0,
      "bandgap": 0.0,
      "sei_score": 0.7949999999999999,
      "cei_score": 0.7825,
      "bulk_modulus": 0.0
    },
    "objectives": [
      10.0,
      1.0,
      0.1050000000000001,
      0.0675,
      1.0
    ],
    "pareto_rank": 0,
    "crowding_distance": 0.0,
    "generation": 2,
    "parent_ids": [
      3038464872208,
      3038464872208
    ],
    "cif_path": "pareto_electrolyte_ga_results\\cifs\\gen1_F64Li64_3038540558480.cif"
  },
  {
    "id": 65,
    "composition": {
      "F": 48,
      "Li": 48
    },
    "lattice_params": {
      "a": 12.133225481707932,
      "b": 12.133225481707932,
      "c": 12.133225481707932,
      "alpha": 90.0,
      "beta": 90.0,
      "gamma": 90.0
    },
    "space_group": 214,
    "properties": {
      "ionic_conductivity": 0.0,
      "bandgap": 0.0,
      "sei_score": 0.7949999999999999,
      "cei_score": 0.7825,
      "bulk_modulus": 0.0
    },
    "objectives": [
      10.0,
      1.0,
      0.1050000000000001,
      0.0675,
      1.0
    ],
    "pareto_rank": 0,
    "crowding_distance": 0.0,
    "generation": 2,
    "parent_ids": [
      3038468574992,
      3038469000976
    ],
    "cif_path": "pareto_electrolyte_ga_results\\cifs\\gen1_F48Li48_3038594500176.cif"
  },
  {
    "id": 66,
    "composition": {
      "Ca": 18,
      "F": 54,
      "Li": 18
    },
    "lattice_params": {
      "a": 9.807321666593564,
      "b": 9.807321666593566,
      "c": 14.656255371701473,
      "alpha": 90.0,
      "beta": 90.0,
      "gamma": 120.00000000000001
    },
    "space_group": 189,
    "properties": {
      "ionic_conductivity": 0.0,
      "bandgap": 0.0,
      "sei_score": 0.7949999999999999,
      "cei_score": 0.7825,
      "bulk_modulus": 0.0
    },
    "objectives": [
      10.0,
      1.0,
      0.1050000000000001,
      0.0675,
      1.0
    ],
    "pareto_rank": 0,
    "crowding_distance": 0.0,
    "generation": 2,
    "parent_ids": [
      3038469295888,
      3038463526992
    ],
    "cif_path": "pareto_electrolyte_ga_results\\cifs\\gen1_Ca18F54Li18_3038594409552.cif"
  },
  {
    "id": 67,
    "composition": {
      "Li": 3,
      "F": 3
    },
    "lattice_params": {
      "a": 3.5471948198370216,
      "b": 3.5471948198370216,
      "c": 10.62892520304238,
      "alpha": 90.0,
      "beta": 90.0,
      "gamma": 119.99999999999999
    },
    "space_group": 189,
    "properties": {
      "ionic_conductivity": 0.0,
      "bandgap": 0.0,
      "sei_score": 0.7949999999999999,
      "cei_score": 0.7825,
      "bulk_modulus": 0.0
    },
    "objectives": [
      10.0,
      1.0,
      0.1050000000000001,
      0.0675,
      1.0
    ],
    "pareto_rank": 0,
    "crowding_distance": 0.0,
    "generation": 2,
    "parent_ids": [
      3038463571600,
      3038463526992
    ],
    "cif_path": "pareto_electrolyte_ga_results\\cifs\\gen1_F3Li3_3038595022992.cif"
  },
  {
    "id": 68,
    "composition": {
      "F": 2,
      "Li": 2
    },
    "lattice_params": {
      "a": 2.8884031200784706,
      "b": 2.8884031200784706,
      "c": 6.627575687600445,
      "alpha": 90.0,
      "beta": 90.0,
      "gamma": 119.99999999999999
    },
    "space_group": 149,
    "properties": {
      "ionic_conductivity": 0.0,
      "bandgap": 0.0,
      "sei_score": 0.7949999999999999,
      "cei_score": 0.7825,
      "bulk_modulus": 0.0
    },
    "objectives": [
      10.0,
      1.0,
      0.1050000000000001,
      0.0675,
      1.0
    ],
    "pareto_rank": 0,
    "crowding_distance": 0.0,
    "generation": 2,
    "parent_ids": [
      3038465775248,
      3038463571600
    ],
    "cif_path": "pareto_electrolyte_ga_results\\cifs\\gen1_F2Li2_3038595592272.cif"
  },
  {
    "id": 69,
    "composition": {
      "Li": 3,
      "F": 3
    },
    "lattice_params": {
      "a": 4.947736034627609,
      "b": 4.94773603462761,
      "c": 3.0120435734352666,
      "alpha": 90.0,
      "beta": 90.0,
      "gamma": 120.00000000000001
    },
    "space_group": 149,
    "properties": {
      "ionic_conductivity": 0.0,
      "bandgap": 0.0,
      "sei_score": 0.7949999999999999,
      "cei_score": 0.7825,
      "bulk_modulus": 0.0
    },
    "objectives": [
      10.0,
      1.0,
      0.1050000000000001,
      0.0675,
      1.0
    ],
    "pareto_rank": 0,
    "crowding_distance": 0.0,
    "generation": 2,
    "parent_ids": [
      3038463526992,
      3038463571600
    ],
    "cif_path": "pareto_electrolyte_ga_results\\cifs\\gen1_F3Li3_3038610127824.cif"
  },
  {
    "id": 70,
    "composition": {
      "F": 64,
      "Li": 64
    },
    "lattice_params": {
      "a": 13.44708491796449,
      "b": 13.44708491796449,
      "c": 9.963974067186138,
      "alpha": 90.0,
      "beta": 90.0,
      "gamma": 90.0
    },
    "space_group": 142,
    "properties": {
      "ionic_conductivity": 0.0,
      "bandgap": 0.0,
      "sei_score": 0.7949999999999999,
      "cei_score": 0.7825,
      "bulk_modulus": 0.0
    },
    "objectives": [
      10.0,
      1.0,
      0.1050000000000001,
      0.0675,
      1.0
    ],
    "pareto_rank": 0,
    "crowding_distance": 0.0,
    "generation": 2,
    "parent_ids": [
      3038465775248,
      3038464872208
    ],
    "cif_path": "pareto_electrolyte_ga_results\\cifs\\gen1_F64Li64_3038469983952.cif"
  },
  {
    "id": 71,
    "composition": {
      "F": 6,
      "Li": 6
    },
    "lattice_params": {
      "a": 6.475195982297429,
      "b": 6.475195982297429,
      "c": 3.296201722702721,
      "alpha": 90.0,
      "beta": 90.0,
      "gamma": 119.99999999999999
    },
    "space_group": 189,
    "properties": {
      "ionic_conductivity": 0.0,
      "bandgap": 0.0,
      "sei_score": 0.7949999999999999,
      "cei_score": 0.7825,
      "bulk_modulus": 0.0
    },
    "objectives": [
      10.0,
      1.0,
      0.1050000000000001,
      0.0675,
      1.0
    ],
    "pareto_rank": 0,
    "crowding_distance": 0.0,
    "generation": 2,
    "parent_ids": [
      3038456457552,
      3038463526992
    ],
    "cif_path": "pareto_electrolyte_ga_results\\cifs\\gen1_F6Li6_3038540629904.cif"
  },
  {
    "id": 72,
    "composition": {
      "F": 48,
      "Li": 48
    },
    "lattice_params": {
      "a": 13.328625290276783,
      "b": 11.56749245678154,
      "c": 6.741326834216215,
      "alpha": 90.0,
      "beta": 90.0,
      "gamma": 90.0
    },
    "space_group": 55,
    "properties": {
      "ionic_conductivity": 0.0,
      "bandgap": 0.0,
      "sei_score": 0.7949999999999999,
      "cei_score": 0.7825,
      "bulk_modulus": 0.0
    },
    "objectives": [
      10.0,
      1.0,
      0.1050000000000001,
      0.0675,
      1.0
    ],
    "pareto_rank": 0,
    "crowding_distance": 0.0,
    "generation": 2,
    "parent_ids": [
      3038466142160,
      3038469000976
    ],
    "cif_path": "pareto_electrolyte_ga_results\\cifs\\gen1_F48Li48_3038609618512.cif"
  },
  {
    "id": 73,
    "composition": {
      "Li": 16,
      "F": 16
    },
    "lattice_params": {
      "a": 7.188504368127034,
      "b": 7.188504368127034,
      "c": 7.188504368127034,
      "alpha": 90.0,
      "beta": 90.0,
      "gamma": 90.0
    },
    "space_group": 214,
    "properties": {
      "ionic_conductivity": 0.0,
      "bandgap": 0.0,
      "sei_score": 0.7949999999999999,
      "cei_score": 0.7825,
      "bulk_modulus": 0.0
    },
    "objectives": [
      10.0,
      1.0,
      0.1050000000000001,
      0.0675,
      1.0
    ],
    "pareto_rank": 0,
    "crowding_distance": 0.0,
    "generation": 2,
    "parent_ids": [
      3038463571600,
      3038469000976
    ],
    "cif_path": "pareto_electrolyte_ga_results\\cifs\\gen1_F16Li16_3038470594576.cif"
  },
  {
    "id": 74,
    "composition": {
      "F": 64,
      "Li": 16,
      "Ca": 24
    },
    "lattice_params": {
      "a": 13.984683684591241,
      "b": 13.984683684591241,
      "c": 8.433501140599573,
      "alpha": 90.0,
      "beta": 90.0,
      "gamma": 90.0
    },
    "space_group": 142,
    "properties": {
      "ionic_conductivity": 0.0,
      "bandgap": 0.0,
      "sei_score": 0.7949999999999999,
      "cei_score": 0.7825,
      "bulk_modulus": 0.0
    },
    "objectives": [
      10.0,
      1.0,
      0.1050000000000001,
      0.0675,
      1.0
    ],
    "pareto_rank": 0,
    "crowding_distance": 0.0,
    "generation": 3,
    "parent_ids": [
      3038463533072,
      3038464874896
    ],
    "cif_path": "pareto_electrolyte_ga_results\\cifs\\gen2_Ca24F64Li16_3038432464016.cif"
  },
  {
    "id": 75,
    "composition": {
      "F": 48,
      "Te": 24,
      "Li": 96
    },
    "lattice_params": {
      "a": 18.02613066414804,
      "b": 18.02613066414804,
      "c": 10.83185934381688,
      "alpha": 90.0,
      "beta": 90.0,
      "gamma": 90.0
    },
    "space_group": 123,
    "properties": {
      "ionic_conductivity": 0.0,
      "bandgap": 0.0,
      "sei_score": 0.7949999999999999,
      "cei_score": 0.7825,
      "bulk_modulus": 0.0
    },
    "objectives": [
      10.0,
      1.0,
      0.1050000000000001,
      0.0675,
      1.0
    ],
    "pareto_rank": 0,
    "crowding_distance": 0.0,
    "generation": 3,
    "parent_ids": [
      3038464874896,
      3038422156304
    ],
    "cif_path": "pareto_electrolyte_ga_results\\cifs\\gen2_F48Li96Te24_3038464693584.cif"
  },
  {
    "id": 76,
    "composition": {
      "Li": 28,
      "F": 28
    },
    "lattice_params": {
      "a": 6.6173169679995825,
      "b": 14.421846357259597,
      "c": 7.340892709709637,
      "alpha": 90.0,
      "beta": 90.0,
      "gamma": 90.0
    },
    "space_group": 55,
    "properties": {
      "ionic_conductivity": 0.0,
      "bandgap": 0.0,
      "sei_score": 0.7949999999999999,
      "cei_score": 0.7825,
      "bulk_modulus": 0.0
    },
    "objectives": [
      10.0,
      1.0,
      0.1050000000000001,
      0.0675,
      1.0
    ],
    "pareto_rank": 0,
    "crowding_distance": 0.0,
    "generation": 3,
    "parent_ids": [
      3038609618512,
      3038596772880
    ],
    "cif_path": "pareto_electrolyte_ga_results\\cifs\\gen2_F28Li28_3038540986768.cif"
  },
  {
    "id": 77,
    "composition": {
      "Li": 42,
      "F": 42
    },
    "lattice_params": {
      "a": 12.645823045516725,
      "b": 12.645823045516725,
      "c": 11.023033934082745,
      "alpha": 90.0,
      "beta": 90.0,
      "gamma": 119.99999999999999
    },
    "space_group": 176,
    "properties": {
      "ionic_conductivity": 0.0,
      "bandgap": 0.0,
      "sei_score": 0.7949999999999999,
      "cei_score": 0.7825,
      "bulk_modulus": 0.0
    },
    "objectives": [
      10.0,
      1.0,
      0.1050000000000001,
      0.0675,
      1.0
    ],
    "pareto_rank": 0,
    "crowding_distance": 0.0,
    "generation": 3,
    "parent_ids": [
      3038594667920,
      3038469538448
    ],
    "cif_path": "pareto_electrolyte_ga_results\\cifs\\gen2_F42Li42_3038411960976.cif"
  },
  {
    "id": 78,
    "composition": {
      "Li": 30,
      "F": 30
    },
    "lattice_params": {
      "a": 8.795891985095457,
      "b": 6.9627681682612765,
      "c": 7.822527250173025,
      "alpha": 90.0,
      "beta": 90.0,
      "gamma": 90.0
    },
    "space_group": 55,
    "properties": {
      "ionic_conductivity": 0.0,
      "bandgap": 0.0,
      "sei_score": 0.7949999999999999,
      "cei_score": 0.7825,
      "bulk_modulus": 0.0
    },
    "objectives": [
      10.0,
      1.0,
      0.1050000000000001,
      0.0675,
      1.0
    ],
    "pareto_rank": 0,
    "crowding_distance": 0.0,
    "generation": 3,
    "parent_ids": [
      3038596009488,
      3038607774032
    ],
    "cif_path": "pareto_electrolyte_ga_results\\cifs\\gen2_F30Li30_3038466576848.cif"
  },
  {
    "id": 79,
    "composition": {
      "Li": 8,
      "F": 8
    },
    "lattice_params": {
      "a": 4.171523782982665,
      "b": 4.171523782982665,
      "c": 12.686675539072173,
      "alpha": 90.0,
      "beta": 90.0,
      "gamma": 90.0
    },
    "space_group": 142,
    "properties": {
      "ionic_conductivity": 0.0,
      "bandgap": 0.0,
      "sei_score": 0.7949999999999999,
      "cei_score": 0.7825,
      "bulk_modulus": 0.0
    },
    "objectives": [
      10.0,
      1.0,
      0.1050000000000001,
      0.0675,
      1.0
    ],
    "pareto_rank": 0,
    "crowding_distance": 0.0,
    "generation": 3,
    "parent_ids": [
      3038541686608,
      3038466867088
    ],
    "cif_path": "pareto_electrolyte_ga_results\\cifs\\gen2_F8Li8_3038468372496.cif"
  }
]